C2D/C2D.py
C2D/__init__.py
C2D-0.0.2.dist-info/LICENSE
C2D-0.0.2.dist-info/METADATA
C2D-0.0.2.dist-info/WHEEL
C2D-0.0.2.dist-info/top_level.txt
C2D-0.0.2.dist-info/RECORD
