Metadata-Version: 2.1
Name: C2D
Version: 0.0.2
Summary: optimal solution to read and save a config file.
Home-page: https://github.com/chavarera/C2D
Author: Ravishankar Chavare
Author-email: chavare.ravi123@gmail.com
License: UNKNOWN
Keywords: c2d,config,config-parser,config-reader
Platform: UNKNOWN
Classifier: Natural Language :: English
Classifier: Programming Language :: Python :: 3.6
Classifier: Operating System :: OS Independent
Requires-Python: >=3.6
